recreate/__init__.py
recreate/recreate.py
recreate-0.3.0.dist-info/licenses/LICENSE
recreate-0.3.0.dist-info/METADATA
recreate-0.3.0.dist-info/WHEEL
recreate-0.3.0.dist-info/entry_points.txt
recreate-0.3.0.dist-info/top_level.txt
recreate-0.3.0.dist-info/RECORD
