Metadata-Version: 2.4
Name: recreate
Version: 0.3.0
Summary: A tool to index files and recreate directory structures with symlinks.
Author-email: Thomas Germer <Thomas.Germer@hhu.de>
License: MIT License
Project-URL: Homepage, https://github.com/99991/recreate
Requires-Python: >=3.9
License-File: LICENSE
Requires-Dist: tqdm
Dynamic: license-file
